duelink/__init__.py
duelink/analog.py
duelink/button.py
duelink/deviceconfiguration.py
duelink/digital.py
duelink/distancesensor.py
duelink/dmx.py
duelink/duelinklib.py
duelink/engine.py
duelink/filesystem.py
duelink/frequency.py
duelink/graphics.py
duelink/humidity.py
duelink/i2c.py
duelink/infrared.py
duelink/otp.py
duelink/pulse.py
duelink/rtc.py
duelink/servo.py
duelink/sound.py
duelink/spi.py
duelink/stream.py
duelink/system.py
duelink/temperature.py
duelink/transport.py
duelink/uart.py
duelink_stdlib_mp-0.0.9.dist-info/METADATA
duelink_stdlib_mp-0.0.9.dist-info/WHEEL
duelink_stdlib_mp-0.0.9.dist-info/top_level.txt
duelink_stdlib_mp-0.0.9.dist-info/RECORD
