Metadata-Version: 2.1
Name: duelink-stdlib-mp
Version: 0.0.9
Summary: GHI Electronics DUELink MicroPython Library.
Home-page: https://www.duelink.com/
Author: GHI Electronics
Author-email: support@ghielectronics.com
License: MIT
Project-URL: Bug Reports, https://github.com/ghi-electronics/duelink-libraries/issues
Project-URL: Source, https://github.com/ghi-electronics/duelink-libraries/tree/main/micropython
Keywords: due,duelink,ghi
Classifier: Programming Language :: Python :: Implementation :: MicroPython
